Metadata-Version: 2.1
Name: konstants
Version: 0.3
Summary: Python package for common math and physics constants.
Home-page: https://github.com/thisisjustinm/constant-list
Author: Justin M.
Author-email: thisisjustinm@outlook.com
License: MIT
Platform: UNKNOWN
